medkey_sdk/__init__.py
medkey_sdk-0.0.2.dist-info/METADATA
medkey_sdk-0.0.2.dist-info/WHEEL
medkey_sdk-0.0.2.dist-info/licenses/LICENSE
medkey_sdk-0.0.2.dist-info/RECORD
